cryptography/__about__.py
cryptography/__init__.py
cryptography/exceptions.py
cryptography/fernet.py
cryptography/utils.py
trolldb/__init__.py
trolldb-1.2.1.dist-info/METADATA
trolldb-1.2.1.dist-info/WHEEL
trolldb-1.2.1.dist-info/entry_points.txt
trolldb-1.2.1.dist-info/top_level.txt
trolldb-1.2.1.dist-info/RECORD
