Metadata-Version: 2.1
Name: trolldb
Version: 1.2.1
Summary: JSON Database but just encrypted
Home-page: https://github.com/ProYT303/trollDB
Author: Walterepic
Author-email: social.proyt303@gmail.com
License: UNKNOWN
Platform: UNKNOWN
Classifier: Programming Language :: Python :: 3
Classifier: Programming Language :: Python :: 3.7
Requires-Dist: cryptography
